kumuniverse/__init__.py
kumuniverse/dynamodb/__init__.py
kumuniverse/halohalo_api/__init__.py
kumuniverse/k8s_model_api/__init__.py
kumuniverse/kafka_msk/__init__.py
kumuniverse/logger/__init__.py
kumuniverse/malacanang_api/__init__.py
kumuniverse/mongodb/__init__.py
kumuniverse/sagemaker_feature_store/__init__.py
kumuniverse/taho_api/__init__.py
kumuniverse/unleash/__init__.py
kumuniverse-0.9.4.dist-info/METADATA
kumuniverse-0.9.4.dist-info/WHEEL
kumuniverse-0.9.4.dist-info/top_level.txt
kumuniverse-0.9.4.dist-info/RECORD
