Metadata-Version: 2.1
Name: kumuniverse
Version: 0.9.4
Summary: Data team shared library for accessing services
Author: Renz Abergos
Author-email: renz@kumu.ph
License: MIT
Classifier: Programming Language :: Python :: 3
Classifier: Operating System :: Unix
Classifier: Operating System :: MacOS :: MacOS X
Classifier: Operating System :: Microsoft :: Windows
Requires-Dist: pymongo
Requires-Dist: pymongo[srv]
Requires-Dist: pymongo[aws]
Requires-Dist: requests
Requires-Dist: UnleashClient
Requires-Dist: boto3
Requires-Dist: pandas
Provides-Extra: databricks
Requires-Dist: pyspark ; extra == 'databricks'
Provides-Extra: kafka
Requires-Dist: kafka-python ; extra == 'kafka'
Provides-Extra: sagemaker
Requires-Dist: sagemaker ; extra == 'sagemaker'
Requires-Dist: redis ; extra == 'sagemaker'
